ecomplexity/ComplexityData.py
ecomplexity/__init__.py
ecomplexity/calc_density.py
ecomplexity/calc_proximity.py
ecomplexity/coicog.py
ecomplexity/density.py
ecomplexity/ecomplexity.py
ecomplexity/log_supermodularity.py
ecomplexity/proximity.py
ecomplexity-0.5.3.dist-info/LICENSE
ecomplexity-0.5.3.dist-info/METADATA
ecomplexity-0.5.3.dist-info/WHEEL
ecomplexity-0.5.3.dist-info/top_level.txt
ecomplexity-0.5.3.dist-info/RECORD
