Metadata-Version: 2.1
Name: ecomplexity
Version: 0.5.3
Summary: Package to calculate economic complexity and associated variables
Home-page: https://github.com/cid-harvard/py-ecomplexity
Author: Shreyas Gadgin Matha
Author-email: shreyas.gm61@gmail.com
License: MIT
Keywords: pandas python networks economics complexity
Classifier: Programming Language :: Python :: 3
Classifier: License :: OSI Approved :: MIT License
Classifier: Operating System :: OS Independent
Requires-Python: >=3
License-File: LICENSE
Requires-Dist: pandas >0.23.0
Requires-Dist: numpy >1.22.0
Requires-Dist: scikit-learn >1.0.0
